[
  {
    "clgPrevUpd": 1654604214886,
    "title": "Advertisement for recruitment, D.A.V. College of Education",
    "date": " Dated: 07/06/22",
    "url": "https://mdu.ac.in/UpFiles/UpPdfFiles/2022/Jun/4_06-07-2022_17-08-35_DAV%20College.PDF"
  },
  {
    "clgPrevUpd": 1654604214886,
    "title": "Notification regarding appointment of Nodal Officer for admissions in UTDs and MDU-CPAS Gurugram",
    "date": " Dated: 07/06/22",
    "url": "https://mdu.ac.in/UpFiles/UpPdfFiles/2022/Jun/4_06-07-2022_15-47-18_Notification-I.PDF"
  },
  {
    "clgPrevUpd": 1654604214886,
    "title": "Advertisement for recruitment, Satya College of Engg. & Tech.",
    "date": " Dated: 06/06/22",
    "url": "https://mdu.ac.in/UpFiles/UpPdfFiles/2022/Jun/4_06-06-2022_17-04-24_advt.%20Satya%20college%20of%20Engg.%20and%20Tech.(for%20the%20post%20of%20teaching%20and%20non%20teaching)%20.pdf"
  },
  {
    "clgPrevUpd": 1654604214886,
    "title": "Advertisement for recruitment, SHRI SHANTI SAGAR JAIN GIRLS COLLEGE OF EDUCATION, FEROZEPUR JHIRKA",
    "date": " Dated: 06/06/22",
    "url": "https://mdu.ac.in/UpFiles/UpPdfFiles/2022/Jun/4_06-06-2022_17-02-54_shri%20shanti%20sagar%20jain%20girls%20college%20of%20education.pdf"
  },
  {
    "clgPrevUpd": 1654604214886,
    "title": "University Level Sangeet Yoga and Yogasana Competition (Group)- IDY2022",
    "date": " Dated: 06/06/22",
    "url": "https://mdu.ac.in/UpFiles/UpPdfFiles/2022/Jun/4_06-06-2022_17-01-12_University%20Level%20Sangeet%20Yoga%20and%20Yogasana%20Competition%20(Group)-%20IDY2022.pdf"
  },
  {
    "clgPrevUpd": 1654604214886,
    "title": "Advertisement for recruitment, Hindu Institute of Management & Technology, Rohtak",
    "date": " Dated: 06/06/22",
    "url": "https://mdu.ac.in/UpFiles/UpPdfFiles/2022/Jun/4_06-06-2022_16-27-13_ADVERTISEMENT%20ATTACHMENTS.pdf"
  },
  {
    "clgPrevUpd": 1654604214886,
    "title": "Advertisement for recruitment, NFG Degree College",
    "date": " Dated: 06/06/22",
    "url": "https://mdu.ac.in/UpFiles/UpPdfFiles/2022/Jun/4_06-06-2022_11-42-12_Letter.pdf"
  },
  {
    "clgPrevUpd": 1654604214886,
    "title": "Advertisement for recruitment, Lord Shiva college of Education",
    "date": " Dated: 06/06/22",
    "url": "https://mdu.ac.in/UpFiles/UpPdfFiles/2022/Jun/4_06-06-2022_11-38-00_Lord%20Shiva%20college%20of%20Education.pdf"
  },
  {
    "clgPrevUpd": 1654604214886,
    "title": "Advertisement for recruitment, Sardar Patel College of Education",
    "date": " Dated: 06/06/22",
    "url": "https://mdu.ac.in/UpFiles/UpPdfFiles/2022/Jun/4_06-06-2022_10-34-10_Non%20Teaching%20Staff%20Advt.pdf"
  },
  {
    "clgPrevUpd": 1654604214886,
    "title": "Advertisement for recruitment, Rashtriya College of Education",
    "date": " Dated: 05/06/22",
    "url": "https://mdu.ac.in/UpFiles/UpPdfFiles/2022/Jun/4_06-05-2022_21-10-07_Rashtriya%20College%20of%20Education.pdf"
  },
  {
    "clgPrevUpd": 1654604214886,
    "title": "Advertisement for recruitment, J.R.Kissan College of Education",
    "date": " Dated: 05/06/22",
    "url": "https://mdu.ac.in/UpFiles/UpPdfFiles/2022/Jun/4_06-05-2022_21-06-42_advt%20letter%20(1).pdf"
  },
  {
    "clgPrevUpd": 1654604214886,
    "title": "Advertisement for recruitment, Delhi Global Institute of Technology, Barhana",
    "date": " Dated: 05/06/22",
    "url": "https://mdu.ac.in/UpFiles/UpPdfFiles/2022/Jun/4_06-05-2022_21-04-52_Delhi%20Global%20Institute%20of%20Technology,%20Barhana.pdf"
  },
  {
    "clgPrevUpd": 1654604214886,
    "title": "Advertisement for recruitment, Tika Ram Girls College",
    "date": " Dated: 05/06/22",
    "url": "https://mdu.ac.in/UpFiles/UpPdfFiles/2022/Jun/4_06-05-2022_21-01-03_Tika%20Ram%20Girls%20College.pdf"
  },
  {
    "clgPrevUpd": 1654604214886,
    "title": "Advertisement for recruitment, CRA College Sonepat",
    "date": " Dated: 05/06/22",
    "url": "https://mdu.ac.in/UpFiles/UpPdfFiles/2022/Jun/4_06-05-2022_20-57-27_CRA%20college%20adv.pdf"
  },
  {
    "clgPrevUpd": 1654604214886,
    "title": "Advertisement for recruitment, South Point Degree College, Sonipat",
    "date": " Dated: 03/06/22",
    "url": "https://mdu.ac.in/UpFiles/UpPdfFiles/2022/Jun/4_06-03-2022_21-50-50_South%20Point%20Degree%20College,%20Sonipat.pdf"
  },
  {
    "clgPrevUpd": 1654604214886,
    "title": "Advertisement for recruitment, South Point College of Law, Sonipat",
    "date": " Dated: 03/06/22",
    "url": "https://mdu.ac.in/UpFiles/UpPdfFiles/2022/Jun/4_06-03-2022_21-44-51_South%20Point%20College%20of%20Law,%20Sonipat.pdf"
  },
  {
    "clgPrevUpd": 1654604214886,
    "title": "Advertisement for recruitment, Laxmi college of education, rathiwas(Jat), Gurugram.",
    "date": " Dated: 03/06/22",
    "url": "https://mdu.ac.in/UpFiles/UpPdfFiles/2022/Jun/4_06-03-2022_21-39-38_adv%20cov%20letter..pdf"
  },
  {
    "clgPrevUpd": 1654604214886,
    "title": "Advertisement for Field Investigator",
    "date": " Dated: 03/06/22",
    "url": "https://mdu.ac.in/UpFiles/UpPdfFiles/2022/Jun/4_06-03-2022_21-16-15_IMG_0003.jpg"
  },
  {
    "clgPrevUpd": 1654604214886,
    "title": "Advertisement for recruitment,  D.H.Lawrence College of education for women, Jhajjar",
    "date": " Dated: 03/06/22",
    "url": "https://mdu.ac.in/UpFiles/UpPdfFiles/2022/Jun/4_06-03-2022_21-11-34_Advertisement%20DHL.pdf"
  },
  {
    "clgPrevUpd": 1654604214886,
    "title": "Advertisement for recruitment,  Shree Mata Mansa Devi Pujasathal Board, Panchkula ",
    "date": " Dated: 01/06/22",
    "url": "https://mdu.ac.in/UpFiles/UpPdfFiles/2022/Jun/4_06-01-2022_21-26-12_WhatsApp%20Image%202022-05-31%20at%204.14.32%20PM.jpeg"
  },
  {
    "clgPrevUpd": 1654604214886,
    "title": "Additional schedule for PG DDE 3rd Sem July 2022 ",
    "date": " Dated: 01/06/22",
    "url": "https://mdu.ac.in/UpFiles/UpPdfFiles/2022/Jun/4_06-01-2022_21-22-08_additional%20schedule%20for%20pg%20dde%203rd%20Sem%20July%202022.pdf"
  },
  {
    "clgPrevUpd": 1654604214886,
    "title": "Notice for Inter-Departmental Debate Competition अंतर-विभागीय वाद-विवाद प्रतियोगिता to be held on 07.06.2022 at 10.00 AM in the Department of Economics",
    "date": " Dated: 01/06/22",
    "url": "https://mdu.ac.in/UpFiles/UpPdfFiles/2022/Jun/4_06-01-2022_21-19-18_Inter-Departmental%20Debate%20Competition%20on%2007.06.2022%20at%2010.00%20AM%20in%20the%20Department%20of%20Economics.pdf"
  },
  {
    "clgPrevUpd": 1654604214886,
    "title": "Advertisement for recruitment, Kanya Mahavidyalaya Kharkhoda",
    "date": " Dated: 01/06/22",
    "url": "https://mdu.ac.in/UpFiles/UpPdfFiles/2022/Jun/4_06-01-2022_21-17-35_Advertisement.pdf"
  },
  {
    "clgPrevUpd": 1654604214886,
    "title": "Inter-Departmental Debate Competition (अंतर-विभागीय वाद-विवाद प्रतियोगिता ) to be held on 07.06.2022 at 10.00 AM in the Department of Economics",
    "date": " Dated: 27/05/22",
    "url": "https://mdu.ac.in/UpFiles/UpPdfFiles/2022/May/4_05-27-2022_11-14-32_Inter-Departmental%20Debate%20Competition%20on%2007.06.2022%20at%2010.00%20AM%20in%20the%20Department%20of%20Economics.pdf"
  },
  {
    "clgPrevUpd": 1654604214886,
    "title": "Notification regarding Summer Vacations",
    "date": " Dated: 21/05/22",
    "url": "https://mdu.ac.in/UpFiles/UpPdfFiles/2022/May/4_05-21-2022_10-25-41_Adobe%20Scan%2020-May-2022.pdf"
  },
  {
    "clgPrevUpd": 1654604214886,
    "title": " \"Notice Regarding Hostel Security Refund for the session 2019-20\"",
    "date": " Dated: 20/05/22",
    "url": "https://mdu.ac.in/UpFiles/UpPdfFiles/2022/May/4_05-19-2022_14-30-10_Scan_20220519.jpg"
  }
]